rr_webapi/__init__.py
rr_webapi/api.py
rr_webapi/eventapi.py
rr_webapi/general.py
rr_webapi/public.py
rr_webapi/endpoints/__init__.py
rr_webapi/endpoints/contests.py
rr_webapi/endpoints/data.py
rr_webapi/endpoints/file.py
rr_webapi/endpoints/history.py
rr_webapi/endpoints/participants.py
rr_webapi/endpoints/rawdata.py
rr_webapi-0.1.7.dist-info/licenses/LICENSE
rr_webapi-0.1.7.dist-info/METADATA
rr_webapi-0.1.7.dist-info/WHEEL
rr_webapi-0.1.7.dist-info/top_level.txt
rr_webapi-0.1.7.dist-info/RECORD
