Metadata-Version: 2.4
Name: rr-webapi
Version: 0.1.7
Summary: Python client library for RaceResult Web API
Author-email: SP Timing Team <dev@sptiming.ch>
Maintainer-email: SP Timing Team <dev@sptiming.ch>
License-Expression: GPL-3.0-or-later
Project-URL: Homepage, https://github.com/SPTiming/python-rr-webapi
Project-URL: Documentation, https://github.com/SPTiming/python-rr-webapi#readme
Project-URL: Repository, https://github.com/SPTiming/python-rr-webapi.git
Project-URL: Bug Reports, https://github.com/SPTiming/python-rr-webapi/issues
Project-URL: Source Code, https://github.com/SPTiming/python-rr-webapi
Keywords: raceresult,api,timing,sports,events,python
Classifier: Development Status :: 4 - Beta
Classifier: Intended Audience :: Developers
Classifier: Operating System :: OS Independent
Classifier: Programming Language :: Python :: 3
Classifier: Programming Language :: Python :: 3.7
Classifier: Programming Language :: Python :: 3.8
Classifier: Programming Language :: Python :: 3.9
Classifier: Programming Language :: Python :: 3.10
Classifier: Programming Language :: Python :: 3.11
Classifier: Programming Language :: Python :: 3.12
Classifier: Topic :: Software Development :: Libraries :: Python Modules
Classifier: Topic :: Internet :: WWW/HTTP :: Dynamic Content
Classifier: Topic :: Software Development :: Libraries :: Application Frameworks
Requires-Python: >=3.7
License-File: LICENSE
Requires-Dist: requests>=2.28.0
Requires-Dist: python-dateutil>=2.8.0
Requires-Dist: python-dotenv>=1.0.0
Provides-Extra: dev
Requires-Dist: pytest>=7.0; extra == "dev"
Requires-Dist: pytest-cov>=4.0; extra == "dev"
Requires-Dist: black>=22.0; extra == "dev"
Requires-Dist: flake8>=5.0; extra == "dev"
Requires-Dist: mypy>=1.0; extra == "dev"
Requires-Dist: build>=0.8; extra == "dev"
Requires-Dist: twine>=4.0; extra == "dev"
Dynamic: license-file
